{
  "meta": {
    "updated": "2026-04-21",
    "dates": "5.1 — 5.5",
    "people": 2,
    "title": "五一假期 · 徒步露营计划",
    "subtitle": "12个候选目的地 · 5天行程 · 从山西高原到云南草甸"
  },
  "recommendation": {
    "id": 1,
    "label": "首选推荐",
    "badge": "全程晴好"
  },
  "destinations": [
    {
      "id": 1,
      "name": "五台山大朝台",
      "location": "山西忻州 · 五台连穿50km",
      "province": "shanxi",
      "provinceName": "山西",
      "tags": ["⭐天气最佳"],
      "lat": "113.666",
      "lng": "39.043",
      "weather": [
        {"d": "5/1", "icon": "🌧️", "text": "小雨/多云", "low": -2, "high": 11, "wind": "北风1-3级"},
        {"d": "5/2", "icon": "⛅", "text": "晴/阴", "low": 0, "high": 16, "wind": "东风1-3级"},
        {"d": "5/3", "icon": "☁️", "text": "阴/阴", "low": 7, "high": 21, "wind": "南风1-3级"},
        {"d": "5/4", "icon": "☁️", "text": "阴/阴", "low": 9, "high": 24, "wind": "西南风1-3级"},
        {"d": "5/5", "icon": "🌤️", "text": "晴间多云", "low": 11, "high": 22, "wind": "西北风4-5级"}
      ],
      "transport": [
        {"type": "✈️", "text": "Day1 广州→太原武宿：海航HU7249 ¥760 2h40m / 南航CZ3377 ¥800 2h40m → 太原→忻州西：高铁约30min ¥30-50"},
        {"type": "✈️", "text": "Day1备选 广州→五台山机场：九元航空直飞 ¥549 3h → 机场→台怀镇：包车约¥200/车 1.5h"},
        {"type": "🚗", "text": "Day2 忻州→徒步起点（鸿门岩）：包车¥约250-300/车 1.5h，拼车¥30-50/人"}
      ],
      "transportMeta": {
        "fastest": "约5h",
        "cheapest": "¥580起",
        "bestRoute": "广州✈️五台山机场 → 台怀镇包车",
        "highlight": "九元航空直飞最省，人均约¥649"
      }
    },
    {
      "id": 2,
      "name": "大理鸟吊山",
      "location": "云南大理州洱源 · 高山草甸",
      "province": "yunnan",
      "provinceName": "云南",
      "tags": ["⚠️季节性开放", "5-10月"],
      "lat": "99.884",
      "lng": "25.959",
      "weather": [
        {"d": "5/1", "icon": "🌧️", "text": "小雨/小雨", "low": 10, "high": 20, "wind": "西南风1-3级"},
        {"d": "5/2", "icon": "🌧️", "text": "小雨/小雨", "low": 10, "high": 22, "wind": "西南风1-3级"},
        {"d": "5/3", "icon": "🌧️", "text": "小雨/小雨", "low": 12, "high": 20, "wind": "南风1-3级"},
        {"d": "5/4", "icon": "🌧️", "text": "小雨/小雨", "low": 8, "high": 16, "wind": "西风1-3级"},
        {"d": "5/5", "icon": "🌦️", "text": "阵雨/多云", "low": 11, "high": 22, "wind": "西南风1-3级"}
      ],
      "transport": [
        {"type": "🚄", "text": "D3802：广州南06:47→大理17:30 ¥653 10h43m"},
        {"type": "🚄", "text": "G2976：广州南11:54→大理21:05 ¥753.5 9h11m"},
        {"type": "🚗", "text": "大理→鸟吊山：包车 ¥200/车 2-2.5h（214国道+盘山土路，建议SUV）"}
      ],
      "transportMeta": {
        "fastest": "约12h",
        "cheapest": "¥853起",
        "bestRoute": "广州南🚄大理 → 鸟吊山包车",
        "highlight": "G2976次时间最佳，需SUV"
      }
    },
    {
      "id": 3,
      "name": "阿西里西韭菜坪",
      "location": "贵州毕节赫章 · 天上花海",
      "province": "guizhou",
      "provinceName": "贵州",
      "tags": ["多雨"],
      "lat": "104.752",
      "lng": "26.998",
      "weather": [
        {"d": "5/1", "icon": "🌧️", "text": "小雨/阴", "low": 10, "high": 17, "wind": "东南风1-3级"},
        {"d": "5/2", "icon": "🌧️", "text": "小雨/小雨", "low": 9, "high": 13, "wind": "东北风1-3级"},
        {"d": "5/3", "icon": "🌧️", "text": "小雨/小雨", "low": 12, "high": 15, "wind": "北风1-3级"},
        {"d": "5/4", "icon": "🌧️", "text": "阴/小雨", "low": 13, "high": 20, "wind": "北风1-3级"},
        {"d": "5/5", "icon": "🌧️", "text": "小雨/阴", "low": 14, "high": 23, "wind": "东南风1-3级"}
      ],
      "transport": [
        {"type": "🚄", "text": "G3796：广州南08:10→毕节站14:56 ¥482 6h46m"},
        {"type": "🚄", "text": "G2246：广州南17:50→毕节站23:40 ¥460 5h50m"},
        {"type": "🚗", "text": "毕节站→韭菜坪：拼车 ¥30-50/人，约1-1.5h；或景区直通车"}
      ],
      "transportMeta": {
        "fastest": "约8h",
        "cheapest": "¥490起",
        "bestRoute": "广州南🚄毕节 → 韭菜坪拼车",
        "highlight": "G2246晚间出发，次日可达"
      }
    },
    {
      "id": 4,
      "name": "乌蒙东坡",
      "location": "贵州六盘水 · 云海高山草原",
      "province": "guizhou",
      "provinceName": "贵州",
      "tags": ["多雨"],
      "lat": "104.667",
      "lng": "26.144",
      "weather": [
        {"d": "5/1", "icon": "☁️", "text": "阴/阴", "low": 12, "high": 18, "wind": "东北风1-3级"},
        {"d": "5/2", "icon": "🌧️", "text": "阴/小雨", "low": 11, "high": 15, "wind": "北风1-3级"},
        {"d": "5/3", "icon": "🌧️", "text": "小雨/阴", "low": 10, "high": 16, "wind": "南风1-3级"},
        {"d": "5/4", "icon": "☁️", "text": "阴/阴", "low": 10, "high": 19, "wind": "西北风1-3级"},
        {"d": "5/5", "icon": "🌦️", "text": "阵雨/阵雨", "low": 13, "high": 23, "wind": "北风1-3级"}
      ],
      "transport": [
        {"type": "🚄", "text": "G3796：广州南08:10→六盘水14:56 ¥482 6h46m"},
        {"type": "🚄", "text": "G2246：广州南17:50→六盘水23:40 ¥460 5h50m"},
        {"type": "🚗", "text": "六盘水站→乌蒙大草原：汽车站大巴 ¥25/人 1h，或打车 ¥150-200"}
      ],
      "transportMeta": {
        "fastest": "约8h",
        "cheapest": "¥485起",
        "bestRoute": "广州南🚄六盘水 → 乌蒙大巴",
        "highlight": "六盘水站大巴仅¥25/人"
      }
    },
    {
      "id": 5,
      "name": "龙脊天路",
      "location": "贵州六盘水六枝特区 · 徒步穿越梯田",
      "province": "guizhou",
      "provinceName": "贵州",
      "tags": ["多雨"],
      "lat": "105.244",
      "lng": "26.126",
      "weather": [
        {"d": "5/1", "icon": "☁️", "text": "阴/阴", "low": 12, "high": 18, "wind": "东北风1-3级"},
        {"d": "5/2", "icon": "🌧️", "text": "阴/小雨", "low": 11, "high": 15, "wind": "北风1-3级"},
        {"d": "5/3", "icon": "🌧️", "text": "小雨/阴", "low": 10, "high": 16, "wind": "南风1-3级"},
        {"d": "5/4", "icon": "☁️", "text": "阴/阴", "low": 10, "high": 19, "wind": "西北风1-3级"},
        {"d": "5/5", "icon": "🌦️", "text": "阵雨/阵雨", "low": 13, "high": 23, "wind": "北风1-3级"}
      ],
      "transport": [
        {"type": "🚄", "text": "G3796：广州南08:10→六盘水14:56 ¥482 6h46m"},
        {"type": "🚄", "text": "G2246：广州南17:50→六盘水23:40 ¥460 5h50m"},
        {"type": "🚗", "text": "六枝南站→龙脊：包车 ¥80-120 40min（推荐）；六盘水站出发约1.5h"}
      ],
      "transportMeta": {
        "fastest": "约8h",
        "cheapest": "¥500起",
        "bestRoute": "广州南🚄六盘水 → 六枝包车",
        "highlight": "六枝南站最近，40min可达"
      }
    },
    {
      "id": 6,
      "name": "老王山",
      "location": "贵州六盘水 · 峰丛峡谷",
      "province": "guizhou",
      "provinceName": "贵州",
      "tags": ["多雨"],
      "lat": "105.221",
      "lng": "26.098",
      "weather": [
        {"d": "5/1", "icon": "☁️", "text": "阴/阴", "low": 12, "high": 18, "wind": "东北风1-3级"},
        {"d": "5/2", "icon": "🌧️", "text": "阴/小雨", "low": 11, "high": 15, "wind": "北风1-3级"},
        {"d": "5/3", "icon": "🌧️", "text": "小雨/阴", "low": 10, "high": 16, "wind": "南风1-3级"},
        {"d": "5/4", "icon": "☁️", "text": "阴/阴", "low": 10, "high": 19, "wind": "西北风1-3级"},
        {"d": "5/5", "icon": "🌦️", "text": "阵雨/阵雨", "low": 13, "high": 23, "wind": "北风1-3级"}
      ],
      "transport": [
        {"type": "🚄", "text": "G3796：广州南08:10→六盘水14:56 ¥482 6h46m"},
        {"type": "🚄", "text": "G2246：广州南17:50→六盘水23:40 ¥460 5h50m"},
        {"type": "🚗", "text": "六盘水站→老王山：打车 ¥80/车，拼车 ¥20-30/人，约1h"}
      ],
      "transportMeta": {
        "fastest": "约7h",
        "cheapest": "¥480起",
        "bestRoute": "广州南🚄六盘水 → 老王山拼车",
        "highlight": "拼车最省¥20-30/人"
      }
    },
    {
      "id": 7,
      "name": "子花山",
      "location": "广西桂林全州",
      "province": "guangxi",
      "provinceName": "广西",
      "tags": [],
      "lat": "110.906",
      "lng": "26.191",
      "weather": [
        {"d": "5/1", "icon": "🌧️", "text": "小雨/小雨", "low": 14, "high": 24, "wind": "东北风1-3级"},
        {"d": "5/2", "icon": "☁️", "text": "阴/阴", "low": 12, "high": 22, "wind": "东风1-3级"},
        {"d": "5/3", "icon": "☁️", "text": "阴/阴", "low": 17, "high": 25, "wind": "东风1-3级"},
        {"d": "5/4", "icon": "🌧️", "text": "小雨/小雨", "low": 18, "high": 22, "wind": "西南风1-3级"},
        {"d": "5/5", "icon": "🌧️", "text": "小雨/阴", "low": 18, "high": 22, "wind": "西南风1-3级"}
      ],
      "transport": [
        {"type": "🚄", "text": "D2966：广州南06:50→全州南10:35 ¥194.5 3h45m"},
        {"type": "🚗", "text": "全州南→子花山：包车 ¥80-120，约30-40km 1-1.5h（无直达公交）"}
      ],
      "transportMeta": {
        "fastest": "约5h",
        "cheapest": "¥234起",
        "bestRoute": "广州南🚄全州南 → 子花山包车",
        "highlight": "D2966早班，无直达公交"
      }
    },
    {
      "id": 8,
      "name": "真穿南",
      "location": "广西桂林资源 · 42km穿越 ⬆1700m · 12-16h",
      "province": "guangxi",
      "provinceName": "广西",
      "tags": ["高强度"],
      "lat": "110.801",
      "lng": "26.105",
      "weather": [
        {"d": "5/1", "icon": "🌧️", "text": "小雨/小雨", "low": 12, "high": 22, "wind": "东北风1-3级"},
        {"d": "5/2", "icon": "☁️", "text": "阴/阴", "low": 11, "high": 21, "wind": "东北风1-3级"},
        {"d": "5/3", "icon": "☁️", "text": "阴/阴", "low": 15, "high": 25, "wind": "东风1-3级"},
        {"d": "5/4", "icon": "🌧️", "text": "小雨/小雨", "low": 17, "high": 20, "wind": "西南风1-3级"},
        {"d": "5/5", "icon": "🌧️", "text": "小雨/阴", "low": 17, "high": 23, "wind": "西南风1-3级"}
      ],
      "transport": [
        {"type": "🚄", "text": "广州南→桂林北 ¥180 2.5h"},
        {"type": "🚌", "text": "桂林北客运站→资源县 ¥45-60 1.5-2h"},
        {"type": "🚗", "text": "资源县城→真穿南：包车 ¥150-200，约1.5-2h山路"}
      ],
      "transportMeta": {
        "fastest": "约6h",
        "cheapest": "¥300起",
        "bestRoute": "广州南🚄桂林北 → 资源 → 包车",
        "highlight": "多段换乘，山路崎岖"
      }
    },
    {
      "id": 9,
      "name": "南风面",
      "location": "湖南郴州策源乡 · 草甸云海",
      "province": "hunan",
      "provinceName": "湖南",
      "tags": [],
      "lat": "114.035",
      "lng": "26.313",
      "weather": [
        {"d": "5/1", "icon": "🌧️", "text": "小雨/小雨", "low": 13, "high": 23, "wind": "北风1-3级"},
        {"d": "5/2", "icon": "🌧️", "text": "小雨/阴", "low": 12, "high": 20, "wind": "北风1-3级"},
        {"d": "5/3", "icon": "☁️", "text": "阴/阴", "low": 16, "high": 26, "wind": "东南风1-3级"},
        {"d": "5/4", "icon": "🌧️", "text": "小雨/小雨", "low": 19, "high": 25, "wind": "南风1-3级"},
        {"d": "5/5", "icon": "🌧️", "text": "小雨/小雨", "low": 19, "high": 21, "wind": "南风1-3级"}
      ],
      "transport": [
        {"type": "🚄", "text": "广州南→郴州西 ¥155-207 1h10m-1h40m"},
        {"type": "🚄", "text": "郴州西→炎陵西 约30min"},
        {"type": "🚌", "text": "炎陵汽车站→策源乡 ¥约15 约40min（7:00-16:30，约30min/班）"},
        {"type": "🚗", "text": "策源乡→梨树洲（登山口）：包车 ¥约50 11km 40min"}
      ],
      "transportMeta": {
        "fastest": "约3.5h",
        "cheapest": "¥195起",
        "bestRoute": "广州南🚄郴州西 → 炎陵 → 策源包车",
        "highlight": "最近的目的地之一"
      }
    },
    {
      "id": 10,
      "name": "瑶峰",
      "location": "湖南郴州 · 高山草甸丹霞",
      "province": "hunan",
      "provinceName": "湖南",
      "tags": [],
      "lat": "113.311",
      "lng": "25.667",
      "weather": [
        {"d": "5/1", "icon": "🌧️", "text": "小雨/小雨", "low": 13, "high": 23, "wind": "北风1-3级"},
        {"d": "5/2", "icon": "🌧️", "text": "小雨/阴", "low": 12, "high": 20, "wind": "北风1-3级"},
        {"d": "5/3", "icon": "☁️", "text": "阴/阴", "low": 16, "high": 26, "wind": "东南风1-3级"},
        {"d": "5/4", "icon": "🌧️", "text": "小雨/小雨", "low": 19, "high": 25, "wind": "南风1-3级"},
        {"d": "5/5", "icon": "🌧️", "text": "小雨/小雨", "low": 19, "high": 21, "wind": "南风1-3级"}
      ],
      "transport": [
        {"type": "🚄", "text": "广州南→郴州西 ¥155-207 1h10m-1h40m"},
        {"type": "🚗", "text": "郴州西→瑶岗仙镇（登山口）：包车 ¥150-200 约1.5h"},
        {"type": "🚌", "text": "或大巴：郴州西站→汽车总站→瑶岗仙镇 ¥35+50"}
      ],
      "transportMeta": {
        "fastest": "约3.5h",
        "cheapest": "¥240起",
        "bestRoute": "广州南🚄郴州西 → 瑶岗仙包车",
        "highlight": "高铁直达后1.5h包车"
      }
    },
    {
      "id": 11,
      "name": "黄梅雪后穿越",
      "location": "广东韶关曲江 · 四峰连穿14-17km ⬆1500m+ · 10-12h",
      "province": "guangdong",
      "provinceName": "广东",
      "tags": ["多雷阵雨"],
      "lat": "113.429",
      "lng": "24.493",
      "weather": [
        {"d": "5/1", "icon": "🌧️", "text": "小雨/小雨", "low": 17, "high": 24, "wind": "北风1-3级"},
        {"d": "5/2", "icon": "🌧️", "text": "小雨/阴", "low": 13, "high": 19, "wind": "北风1-3级"},
        {"d": "5/3", "icon": "☁️", "text": "阴/阴", "low": 16, "high": 25, "wind": "东北风1-3级"},
        {"d": "5/4", "icon": "🌧️", "text": "阴/小雨", "low": 21, "high": 27, "wind": "南风1-3级"},
        {"d": "5/5", "icon": "🌧️", "text": "小雨/小雨", "low": 19, "high": 22, "wind": "南风1-3级"}
      ],
      "transport": [
        {"type": "🚄", "text": "广州南→韶关站 ¥82-115 45-60min"},
        {"type": "🚗", "text": "韶关站→天池山庄（登山口）：包车 ¥150-200，约45-60min"}
      ],
      "transportMeta": {
        "fastest": "约2.5h",
        "cheapest": "¥157起",
        "bestRoute": "广州南🚄韶关 → 天池山庄包车",
        "highlight": "最近！高铁1h即达"
      }
    },
    {
      "id": 12,
      "name": "梅子岭古道",
      "location": "广东清远阳山 · 石阶古道",
      "province": "guangdong",
      "provinceName": "广东",
      "tags": ["多雷阵雨"],
      "lat": "112.855",
      "lng": "24.416",
      "weather": [
        {"d": "5/1", "icon": "🌧️", "text": "小雨/小雨", "low": 17, "high": 25, "wind": "西北风1-3级"},
        {"d": "5/2", "icon": "☁️", "text": "阴/阴", "low": 14, "high": 21, "wind": "北风1-3级"},
        {"d": "5/3", "icon": "☁️", "text": "阴/阴", "low": 19, "high": 27, "wind": "北风1-3级"},
        {"d": "5/4", "icon": "🌧️", "text": "小雨/小雨", "low": 20, "high": 26, "wind": "东南风1-3级"},
        {"d": "5/5", "icon": "🌧️", "text": "小雨/小雨", "low": 21, "high": 22, "wind": "东南风1-3级"}
      ],
      "transport": [
        {"type": "🚌", "text": "广州省站/天河站→阳山汽车站 ¥60-73 3-4h"},
        {"type": "🚗", "text": "阳山汽车站→梅子岭登山口：包车 ¥约100-120，约30-40min"}
      ],
      "transportMeta": {
        "fastest": "约5h",
        "cheapest": "¥110起",
        "bestRoute": "广州🚌阳山 → 梅子岭包车",
        "highlight": "大巴最省，但需3-4h"
      }
    }
  ],
  "gear": {
    "clothing": [
      {"name": "UTO羊毛速干衣上衣与裤子", "price": 498},
      {"name": "迪卡侬WEDZE滑雪内衣BL500上衣+打底裤", "price": 200},
      {"name": "迪卡侬QUECHUA H500防泼水长裤", "price": 272},
      {"name": "迪卡侬QUECHUA防水徒步罩裤MH100", "price": 100},
      {"name": "迪卡侬QUECHUA防水徒步鞋中帮MH500", "price": 550},
      {"name": "迪卡侬QUECHUA摇粒绒保暖紧身裤MH100", "price": 60},
      {"name": "拓路者锦衣卫硬壳冲锋衣", "price": 654},
      {"name": "拓路者立领羽绒服700蓬127g", "price": 421},
      {"name": "拓路者羊毛袜3双", "price": 157},
      {"name": "挪客冬季徒步手套", "price": 69},
      {"name": "挪客羊毛帽", "price": 129}
    ],
    "hiking": [
      {"name": "挪客登山包氦70L", "price": 998},
      {"name": "挪客云尚PRO双人徒步帐篷", "price": 1383},
      {"name": "挪客单人徒野R5.8充气睡垫", "price": null},
      {"name": "黑冰睡袋Z1000M（-18℃/800蓬/1000g）", "price": 2703},
      {"name": "挪客登山杖初雪UL共2根", "price": 251},
      {"name": "火枫露营炉G2套装", "price": 165},
      {"name": "挪客头灯", "price": 99}
    ]
  },
  "todos": [
    {"text": "天气预报（行政区划15天）", "done": true},
    {"text": "经纬度坐标记录", "done": true},
    {"text": "交通方式（携程查询）", "done": true},
    {"text": "行程天数（5.1-5.5）", "done": true},
    {"text": "装备清单确认", "done": false},
    {"text": "同行人员（2人）", "done": true}
  ]
}
